main.py
pdf_compressor.py
pdf_editor.py
pdf_ocr.py
pdf_page_manager.py
shift_cloud_cli.py
shift_converter.py
shift_cli-1.0.6.dist-info/METADATA
shift_cli-1.0.6.dist-info/WHEEL
shift_cli-1.0.6.dist-info/entry_points.txt
shift_cli-1.0.6.dist-info/top_level.txt
shift_cli-1.0.6.dist-info/RECORD
