Metadata-Version: 2.4
Name: shift-cli
Version: 1.0.6
Summary: Universal document and PDF toolkit - Convert, compress, edit, and process documents
Home-page: https://github.com/adamn1225/shift
Author: Adam N.
Author-email: anoah1225@gmail.com
Classifier: Development Status :: 4 - Beta
Classifier: Intended Audience :: Developers
Classifier: License :: OSI Approved :: MIT License
Classifier: Programming Language :: Python :: 3
Classifier: Programming Language :: Python :: 3.8
Classifier: Programming Language :: Python :: 3.9
Classifier: Programming Language :: Python :: 3.10
Classifier: Programming Language :: Python :: 3.11
Classifier: Topic :: Text Processing
Classifier: Topic :: Utilities
Requires-Python: >=3.8
Requires-Dist: pypdf>=5.9.0
Requires-Dist: fpdf2>=2.8.0
Requires-Dist: markdown>=3.8.0
Requires-Dist: beautifulsoup4>=4.13.0
Requires-Dist: python-docx>=1.2.0
Requires-Dist: docx2python>=3.5.0
Requires-Dist: pdfkit>=1.0.0
Requires-Dist: html2text>=2025.4.0
Requires-Dist: Pillow>=11.0.0
Requires-Dist: pymupdf>=1.23.0
Requires-Dist: pytesseract>=0.3.10
Dynamic: author
Dynamic: author-email
Dynamic: classifier
Dynamic: description
Dynamic: description-content-type
Dynamic: home-page
Dynamic: requires-dist
Dynamic: requires-python
Dynamic: summary
